[
  {
    "type": "img",
    "src": "/assets/2020-10-01-autumn/bilibili-autumn-1.webp",
    "width": 3000,
    "height": 250,
    "transform": [1, 0, 0, 1, 0, 0],
    "xSpeed": 0.013,
    "blur": [4, 1, 7],
    "opacity": [1, 1, 1]
  },
  {
    "type": "img",
    "src": "/assets/2020-10-01-autumn/bilibili-autumn-2.webp",
    "width": 1800,
    "height": 165,
    "transform": [1, 0, 0, 1, 0, 0],
    "xSpeed": 0.0169,
    "blur": [0, 6, 6],
    "opacity": [1, 1, 1]
  },
  {
    "type": "img",
    "src": "/assets/2020-10-01-autumn/bilibili-autumn-3.webp",
    "width": 3000,
    "height": 250,
    "transform": [1, 0, 0, 1, 0, 0],
    "xSpeed": 0.02197,
    "blur": [1, 4, 2],
    "opacity": [1, 1, 1]
  },
  {
    "type": "img",
    "src": "/assets/2020-10-01-autumn/bilibili-autumn-4.webp",
    "width": 1800,
    "height": 150,
    "transform": [1, 0, 0, 1, 0, 0],
    "xSpeed": 0.02856,
    "blur": [4, 8, 0],
    "opacity": [1, 1, 1]
  },
  {
    "type": "img",
    "src": "/assets/2020-10-01-autumn/bilibili-autumn-5.webp",
    "width": 1800,
    "height": 150,
    "transform": [1, 0, 0, 1, 0, 0],
    "xSpeed": 0.03713,
    "blur": [5, 10, 0],
    "opacity": [1, 1, 1]
  },
  {
    "type": "img",
    "src": "/assets/2020-10-01-autumn/bilibili-autumn-6.webp",
    "width": 1920,
    "height": 180,
    "transform": [1, 0, 0, 1, 0, 0],
    "xSpeed": 0.04827,
    "blur": [6, 10, 1],
    "opacity": [1, 1, 1]
  }
]
